[
  {
    "titre": "Javascript",
    "couleur": "red",
    "id": "signet001",
    "dateModif": "05 Janvier 2021"
  },
  {
    "titre": "HTML",
    "couleur":"red",
    "id": "signet002",
    "dateModif": "06 Janvier 2021"
  },
  {
    "titre": "React",
    "couleur": "red",
    "id": "signet003",
    "dateModif": "05 Janvier 2021"
  },
  {
    "titre": "C#",
    "couleur": "red",
    "id": "signet004",
    "dateModif": "05 Janvier 2021"
  },
  {
    "titre": "Cadriciels",
    "couleur": "red",
    "id": "signet005",
    "dateModif": "10 Janvier 2021"
  },
  {
    "titre": "CSS",
    "couleur": "red",
    "id": "signet006",
    "dateModif": "08 Janvier 2021"
  },
  {
    "titre": "Unity",
    "couleur": "red",
    "id": "signet007",
    "dateModif": "05 Janvier 2021"
  },
  {
    "titre": "Firebase",
    "couleur":"red",
    "id": "signet008",
    "dateModif": "05 Janvier 2021"
  }
]